{
  "posts": [
    {
      "author": "Nerfi666",
      "title": "China",
      "likes": 11,
      "id": 1
    },
    {
      "title": "Bankok",
      "author": "Nerfi666",
      "likes": 0,
      "id": 2
    },
    {
      "author": "Nerfi666",
      "title": "Quito",
      "likes": 12,
      "id": 3
    },
    {
      "title": "Paris",
      "author": "Nerfi666",
      "likes": 0,
      "id": 4
    },
    {
      "author": "Nerfi666",
      "title": "Krakow",
      "likes": 4,
      "id": 5
    },
    {
      "author": "Nerfi666",
      "title": "Barcelona",
      "category": "travel",
      "likes": 15,
      "id": 6
    },
    {
      "author": "Nerfi666",
      "title": "Madrid",
      "category": "travel",
      "likes": 17,
      "id": 7
    }
  ],
  "comments": [],
  "profile": {
    "name": "typicode"
  }
}